{"customizations_configuration.md":"6d295cb5","colors_border-color.md":"e40cd570","colors_text-color.md":"ab281c3f","core-concepts_ui-centric.md":"28377dcd","core-concepts_theme-management.md":"bb0ac1fb","index.md":"18605cb5","colors_dark-theme.md":"0ece921f","core-concepts_adding-custom-styles.md":"a5c2c263","mixins_margins.md":"f5df3c5f","customizations_opacity.md":"c001b6da","mixins_gradients.md":"da4b6421","widgets_tw-container.md":"b51a7597","widgets_tw-column.md":"7bf1bf11","methods_gestures.md":"a00ad662","methods_alignment.md":"e6e2eed4","introduction.md":"f79db172","mixins_alignment.md":"0a1f7bee","installation.md":"6be7cc1e","widgets_tw-padding.md":"fae4ad69","methods_shadow.md":"83204a32","methods_margins.md":"b2727b5c","partials_gesture-mixin-extensions.md":"cf8e9a30","mixins_shadow.md":"eb0b20eb","widgets_tw-stack.md":"7a0ff29a","widgets_tw-image.md":"be041467","colors_gradient-color.md":"f9f35aa7","mixins_paddings.md":"74d68e7e","widgets_tw-button.md":"50cc0ea7","mixins_gestures.md":"49dcf13a","methods_colors.md":"bdb9552f","widgets_tw-text.md":"61c4f30e","mixins_size.md":"28142edd","partials_margin-mixin-extensions.md":"9480a62b","core-concepts_dark-mode.md":"c4344617","widgets_tw-wrap.md":"72e7615e","effects_box-shadow.md":"ed9bc698","mixins_colors.md":"c27e864c","mixins_border.md":"dc259e2c","customizations_font-sizes.md":"2d315fbd","methods_paddings.md":"c28da1d6","core-concepts_reusable-styles.md":"d44ae2c9","effects_opacity.md":"06f1c0b5","methods_gradients.md":"a6a914be","colors_background-color.md":"412801a2","methods_roundness.md":"e65d8386","widgets_tw-inkwell.md":"3e80b02d","customizations_colors.md":"f467b240","mixins_roundness.md":"d74effdf","customizations_spacing.md":"8878495c","widgets_tw-row.md":"c67d16b6"}
